benchmarks/__init__.py
benchmarks/estimator_benchmarks.py
benchmarks/triangle_benchmarks.py
trikit/__init__.py
trikit/triangle.py
trikit/utils.py
trikit/datasets/AutoLiabMedical.csv
trikit/datasets/GLReinsurance2004.csv
trikit/datasets/RAA.csv
trikit/datasets/SingaporeInjury.csv
trikit/datasets/SingaporeProperty.csv
trikit/datasets/TaylorAshe83.csv
trikit/datasets/__init__.py
trikit/datasets/amw09.csv
trikit/datasets/lrdb.csv
trikit/estimators/__init__.py
trikit/estimators/base.py
trikit/estimators/bootstrap.py
trikit/estimators/glm.py
trikit/estimators/mack.py
trikit/tests/__init__.py
trikit/tests/test_datasets_ut.py
trikit/tests/test_estimators_ut.py
trikit/tests/test_triangle_ut.py
trikit/tests/test_utils_ut.py
trikit-0.3.6.dist-info/LICENSE
trikit-0.3.6.dist-info/METADATA
trikit-0.3.6.dist-info/WHEEL
trikit-0.3.6.dist-info/top_level.txt
trikit-0.3.6.dist-info/RECORD
