Metadata-Version: 2.1
Name: trikit
Version: 0.3.6
Summary: A Pythonic Approach to Actuarial Reserving
Home-page: https://github.com/trikit/trikit
Author: James D. Triveri
Author-email: james.triveri@gmail.com
License: MIT
Keywords: actuarial finance reserving chainladder insurance
Classifier: Development Status :: 4 - Beta
Classifier: Programming Language :: Python :: 3 :: Only
Classifier: License :: OSI Approved :: MIT License
Classifier: Topic :: Scientific/Engineering :: Mathematics
Classifier: Operating System :: OS Independent
License-File: LICENSE
Requires-Dist: numpy ==1.26.2
Requires-Dist: scipy ==1.3
Requires-Dist: pandas ==2.1.4
Requires-Dist: matplotlib ==3.8.2
Requires-Dist: seaborn ==0.13
Requires-Dist: statsmodels ==0.14
